hazma/__init__.py
hazma/background_model.py
hazma/cmb.py
hazma/constraint_parameters.py
hazma/decay.py
hazma/flux_measurement.py
hazma/gamma_ray.py
hazma/gamma_ray_parameters.py
hazma/hazma_errors.py
hazma/parameters.py
hazma/positron_spectra.py
hazma/rambo.py
hazma/axial_vector_mediator/__init__.py
hazma/axial_vector_mediator/_axial_vector_mediator_cross_sections.py
hazma/axial_vector_mediator/_axial_vector_mediator_positron_spectra.py
hazma/axial_vector_mediator/avm_msqrd.py
hazma/axial_vector_mediator/axial_vector_mediator_cross_sections.py
hazma/axial_vector_mediator/axial_vector_mediator_parameters.py
hazma/cmb_data/f_eff_ep.dat
hazma/cmb_data/f_eff_g.dat
hazma/decay_helper_functions/__init__.py
hazma/decay_helper_functions/decay_charged_kaon.c
hazma/decay_helper_functions/decay_charged_kaon.cpython-36m-darwin.so
hazma/decay_helper_functions/decay_charged_kaon.pxd
hazma/decay_helper_functions/decay_charged_kaon.pyx
hazma/decay_helper_functions/decay_charged_pion.c
hazma/decay_helper_functions/decay_charged_pion.cpython-36m-darwin.so
hazma/decay_helper_functions/decay_charged_pion.pxd
hazma/decay_helper_functions/decay_charged_pion.pyx
hazma/decay_helper_functions/decay_electron.pxd
hazma/decay_helper_functions/decay_electron.pyx
hazma/decay_helper_functions/decay_long_kaon.c
hazma/decay_helper_functions/decay_long_kaon.cpython-36m-darwin.so
hazma/decay_helper_functions/decay_long_kaon.pxd
hazma/decay_helper_functions/decay_long_kaon.pyx
hazma/decay_helper_functions/decay_muon.c
hazma/decay_helper_functions/decay_muon.cpython-36m-darwin.so
hazma/decay_helper_functions/decay_muon.pxd
hazma/decay_helper_functions/decay_muon.pyx
hazma/decay_helper_functions/decay_neutral_pion.c
hazma/decay_helper_functions/decay_neutral_pion.cpython-36m-darwin.so
hazma/decay_helper_functions/decay_neutral_pion.pxd
hazma/decay_helper_functions/decay_neutral_pion.pyx
hazma/decay_helper_functions/decay_short_kaon.c
hazma/decay_helper_functions/decay_short_kaon.cpython-36m-darwin.so
hazma-1.1.dist-info/LICENSE
hazma-1.1.dist-info/METADATA
hazma-1.1.dist-info/WHEEL
hazma-1.1.dist-info/top_level.txt
hazma-1.1.dist-info/RECORD
