Metadata-Version: 2.1
Name: hazma
Version: 1.1
Summary: Python package for computing indirect detection constraints on sub-GeV dark matter.
Home-page: http://hazma.readthedocs.io
Author: Logan Morrison and Adam Coogan
Author-email: loanmorr@ucsc.edu
Maintainer: Logan Morrison
Maintainer-email: loanmorr@ucsc.edu
License: gpl-3.0
Download-URL: https://github.com/LoganAMorrison/Hazma
Keywords: dark-matter mev-dark-matter gamma-ray-spectra
Platform: MacOS and Linux
Classifier: Programming Language :: Python
Requires-Dist: pip (>=9.0.1)
Requires-Dist: matplotlib (>=2.2.3)
Requires-Dist: scipy (>=1.0.0)
Requires-Dist: numpy (>=1.13.3)
Requires-Dist: cython (>=0.27.3)
Requires-Dist: numpydoc (>=0.7.0)
Requires-Dist: scikit-image (>=0.14)
Requires-Dist: setuptools (>=27.3)
Requires-Dist: flake8 (>=3.5.0)
